{
  "versions": [
    {
      "version": "v5.00",
      "date": "2026-04-25",
      "changes": [
        "🚀 Version 5 Update",
        "Stability Improvements & Fixes",

        "✨ Updated & Fixed",
        "User List Follow Indicator Fixed",
        "Change Chat Background Fixed",
        "Remove Empty Space Fixed",
        "Hide Opened Media Fixed",

        "➕ Added Features (Miscellaneous)",
        "Story Timestamp Options Added",
        "Sanitize URLs Added",
        "Story Ring Size Re-Added",

        "❌ Removed",
        "Copy Bio Option Removed"
      ]
    },
    {
      "version": "v4.00",
      "date": "2026-03-16",
      "changes": [
        "🚀 Version 4 Major Update",

        "✨ Special Features",
        "Copy Bio + Auto Save",
        "Copy Comments + Auto Save",
        "Once Media Download",
        "Marked as Seen Icon (Ghost Mode BETA)",
        "User List Follow Indicator (BETA)",
        "Auto Cache Cleaner",
        "Change Chat Background",

        "⚙️ Extra",
        "Remove Empty Space (Experimental)",
        "50+ Languages Added"
      ]
    },
    {
      "version": "v3.00",
      "date": "2026-02-10",
      "changes": [
        "🚀 Version 3 Major Update",

        "✨ Special Features",
        "Redesigned Notes Layout",
        "Content Layout customization",
        "Username → Messages action",
        "Story Search + Like Animation",
        "Story Ring Size control",
        "Pinch Zoom (Stories & Reels)",
        "10 Min Reels Upload",
        "Advanced Repost",
        "Enhanced Media Quality",
        "Valentine Theme & Sticker",

        "⚙️ Extra",
        "Disable Story Auto-Next"
      ]
    },
    {
      "version": "v2.00",
      "date": "2026-01-25",
      "changes": [
        "🚀 Version 2 Major Update",

        "🧘 Distraction Free Mode",
        "Hide suggested posts",
        "Hide reels from feed",
        "Hide Stories Tray",
        "Clean and focused home feed",

        "🙈 Hidden Mentions",
        "View Hidden Mentions in Stories",
        "View Hidden Mentions in Highlights",

        "🎨 UI Improvements",
        "Polished layouts",
        "Minor UI fixes",
        "Better spacing and alignment",

        "⚡ Performance",
        "Faster app loading",
        "Improved stability"
      ]
    },
    {
      "version": "v1.00",
      "date": "2026-01-14",
      "changes": [
        "🚀 Initial Release",
        "InstaZen first public release",
        "Custom InstaZen settings panel",
        "Modern dark UI design",
        "Optimized performance",

        "👻 Ghost Mode",
        "Hide typing indicator",
        "Hide story views",
        "Hide live viewing status",
        "View one-time media again",
        "Hide screenshot detection",
        "Hide replay status",
        "Hide seen status in DM",

        "⭐ Special Features",
        "Follow indicator",
        "Full screen reels",
        "Priority stories",
        "120 sec music stories",
        "Enhanced media quality",

        "🎨 Emojis & Fonts",
        "Change emoji style",
        "Emoji menu via icon long press",

        "⬇️ Download",
        "Improved download options",

        "🧰 Stability",
        "Reduced lag",
        "Bug fixes"
      ]
    }
  ]
}
