{
  "upi": {
    "qr_image": "https://raw.githubusercontent.com/AmanOjha/InstaZen-Config/main/images/upi_qr.png",
    "upi_id": "amanojha@paytm"
  },
  
  "paypal": {
    "qr_image": "https://raw.githubusercontent.com/AmanOjha/InstaZen-Config/main/images/paypal_qr.png",
    "paypal_link": "https://paypal.me/AmanOjha"
  },
  
  "youtube": {
    "channel_link": "https://www.youtube.com/channel/UC1234567890/join"
  },
  
  "top_donations": [
    {
      "emoji": "🩵",
      "name": "Rahul Sharma",
      "amount": "₹2,000"
    },
    {
      "emoji": "💜",
      "name": "Amit Kumar",
      "amount": "₹1,500"
    },
    {
      "emoji": "💚",
      "name": "Priya Singh",
      "amount": "₹1,000"
    },
    {
      "emoji": "🧡",
      "name": "Vijay Patel",
      "amount": "₹500"
    },
    {
      "emoji": "💛",
      "name": "Neha Gupta",
      "amount": "₹300"
    }
  ],
  
  "thank_you_message": "Thanks to all our supporters! 💕"
}
